aorlib/__init__.py
aorlib/aorlib.py
aorlib-0.0.1a0.dist-info/LICENSE
aorlib-0.0.1a0.dist-info/METADATA
aorlib-0.0.1a0.dist-info/WHEEL
aorlib-0.0.1a0.dist-info/top_level.txt
aorlib-0.0.1a0.dist-info/RECORD
