Metadata-Version: 2.1
Name: aorlib
Version: 0.0.1a0
Summary: A python library with the ability to interact with Arch Official Repository
Home-page: https://github.com/tonybenoy/aorlib
Author: Tony Benoy
Author-email: me@tonybenoy.com
License: UNKNOWN
Keywords: Arch Linux AUR Arch Offical Repository pacman paur
Platform: UNKNOWN
Classifier: Programming Language :: Python :: 3
Classifier: License :: OSI Approved :: BSD License
Classifier: Operating System :: OS Independent
Classifier: Development Status :: 2 - Pre-Alpha
Requires-Python: >=3.7
Requires-Dist: httpx
Provides-Extra: dev
Requires-Dist: black ; extra == 'dev'
Requires-Dist: pylint ; extra == 'dev'
Requires-Dist: isort ; extra == 'dev'
Requires-Dist: mypy ; extra == 'dev'
